pywebcopy/__init__.py
pywebcopy/__main__.py
pywebcopy/__version__.py
pywebcopy/configs.py
pywebcopy/core.py
pywebcopy/elements.py
pywebcopy/helpers.py
pywebcopy/parsers.py
pywebcopy/schedulers.py
pywebcopy/session.py
pywebcopy/urls.py
pywebcopy-7.1.dist-info/licenses/LICENSE
pywebcopy-7.1.dist-info/METADATA
pywebcopy-7.1.dist-info/WHEEL
pywebcopy-7.1.dist-info/top_level.txt
pywebcopy-7.1.dist-info/RECORD
