Metadata-Version: 2.4
Name: pywebcopy
Version: 7.1
Summary: Python library to clone/archive pages or sites from the Internet.
Home-page: https://github.com/rajatomar788/pywebcopy/
Author: Raja Tomar
Author-email: rajatomar788@gmail.com
License: Apache Software License
Classifier: License :: OSI Approved :: Apache Software License
Classifier: Programming Language :: Python
Classifier: Programming Language :: Python :: 2.6
Classifier: Programming Language :: Python :: 2.7
Classifier: Programming Language :: Python :: 3.6
Classifier: Programming Language :: Python :: 3.7
Classifier: Programming Language :: Python :: 3.8
Classifier: Programming Language :: Python :: 3.9
Classifier: Programming Language :: Python :: 3.10
Classifier: Programming Language :: Python :: 3.11
Classifier: Programming Language :: Python :: 3.12
Classifier: Programming Language :: Python :: Implementation :: CPython
Classifier: Programming Language :: Python :: Implementation :: PyPy
License-File: LICENSE
Requires-Dist: setuptools
Requires-Dist: six
Requires-Dist: requests
Requires-Dist: lxml
Requires-Dist: lxml_html_clean
Requires-Dist: cachecontrol
Dynamic: author
Dynamic: author-email
Dynamic: classifier
Dynamic: description
Dynamic: description-content-type
Dynamic: home-page
Dynamic: license
Dynamic: license-file
Dynamic: requires-dist
Dynamic: summary
